./.gitignore
./PKG-INFO
./README.md
./agent_genesis_mcp.py
./indexing_tools.py
./pyproject.toml
./scheduler.py
./test_mcp.py
./test_mcp_2025_compliance.py
agent_genesis_mcp-1.2.0.dist-info/METADATA
agent_genesis_mcp-1.2.0.dist-info/WHEEL
agent_genesis_mcp-1.2.0.dist-info/entry_points.txt
agent_genesis_mcp-1.2.0.dist-info/RECORD
