Metadata-Version: 2.4
Name: agent-genesis-mcp
Version: 1.2.0
Summary: MCP server for searching Claude Code conversation history via Agent Genesis
Project-URL: Homepage, https://github.com/agentgenesis/agent-genesis
Project-URL: Documentation, https://github.com/agentgenesis/agent-genesis#readme
Project-URL: Repository, https://github.com/agentgenesis/agent-genesis
Project-URL: Issues, https://github.com/agentgenesis/agent-genesis/issues
Author: Agent Genesis Contributors
License: MIT
Keywords: ai-assistant,claude,claude-code,conversation-history,mcp,semantic-search
Classifier: Development Status :: 4 - Beta
Classifier: Intended Audience :: Developers
Classifier: License :: OSI Approved :: MIT License
Classifier: Programming Language :: Python :: 3
Classifier: Programming Language :: Python :: 3.10
Classifier: Programming Language :: Python :: 3.11
Classifier: Programming Language :: Python :: 3.12
Classifier: Topic :: Scientific/Engineering :: Artificial Intelligence
Classifier: Topic :: Software Development :: Libraries :: Python Modules
Requires-Python: >=3.10
Requires-Dist: fastmcp>=2.3.0
Requires-Dist: requests>=2.31.0
Provides-Extra: dev
Requires-Dist: black>=23.0.0; extra == 'dev'
Requires-Dist: pytest-asyncio>=0.21.0; extra == 'dev'
Requires-Dist: pytest>=7.4.0; extra == 'dev'
Requires-Dist: ruff>=0.1.0; extra == 'dev'
